ARS_Test/__init__.py
ARS_Test/cli.py
ARS_Test/semantic_test.py
ARS_Test-0.0.2.dist-info/LICENSE.txt
ARS_Test-0.0.2.dist-info/METADATA
ARS_Test-0.0.2.dist-info/WHEEL
ARS_Test-0.0.2.dist-info/entry_points.txt
ARS_Test-0.0.2.dist-info/top_level.txt
ARS_Test-0.0.2.dist-info/RECORD
