Metadata-Version: 2.1
Name: ARS-Test
Version: 0.0.2
Summary: Python package for ARS pass/fail test
Home-page: https://github.com/NCATSTranslator/ARS_Test
Author: Shervin Abdollahi, Mark Williams
Author-email: shervin.abdollahi@Nih.gov, mark.williams5@nih.gov
License: Public Domain
Platform: UNKNOWN
Classifier: Development Status :: 2 - Pre-Alpha
Classifier: Natural Language :: English
Classifier: Programming Language :: Python :: 3
License-File: LICENSE.txt
Requires-Dist: requests
Requires-Dist: httpx
Requires-Dist: reasoner-validator
Requires-Dist: numpy
Requires-Dist: attrs (>=20.3.0)
Requires-Dist: click
Requires-Dist: twine
